pyslurmutils/__init__.py
pyslurmutils/apps/__init__.py
pyslurmutils/apps/__main__.py
pyslurmutils/apps/cli/__init__.py
pyslurmutils/apps/cli/cancel.py
pyslurmutils/apps/cli/common.py
pyslurmutils/apps/cli/diff.py
pyslurmutils/apps/cli/status.py
pyslurmutils/apps/cli/submit.py
pyslurmutils/client/__init__.py
pyslurmutils/client/defaults.py
pyslurmutils/client/errors.py
pyslurmutils/client/log_utils.py
pyslurmutils/client/os_utils.py
pyslurmutils/client/url_utils.py
pyslurmutils/client/utils.py
pyslurmutils/client/job_io/__init__.py
pyslurmutils/client/job_io/local/__init__.py
pyslurmutils/client/job_io/local/_connection_base.py
pyslurmutils/client/job_io/local/_connection_file.py
pyslurmutils/client/job_io/local/_connection_tcp.py
pyslurmutils/client/job_io/local/_executor.py
pyslurmutils/client/job_io/local/_proxy_base.py
pyslurmutils/client/job_io/local/_proxy_local.py
pyslurmutils/client/job_io/local/_proxy_remote.py
pyslurmutils/client/job_io/remote/__init__.py
pyslurmutils/client/job_io/remote/_base.py
pyslurmutils/client/job_io/remote/_file.py
pyslurmutils/client/job_io/remote/_tcp.py
pyslurmutils/client/rest/__init__.py
pyslurmutils/client/rest/base.py
pyslurmutils/client/rest/pyconn.py
pyslurmutils/client/rest/script.py
pyslurmutils/client/rest/api/__init__.py
pyslurmutils/client/rest/api/slurm_access.py
pyslurmutils/client/rest/api/slurm_auth.py
pyslurmutils/client/rest/api/slurm_endpoints.py
pyslurmutils/client/rest/api/slurm_logs.py
pyslurmutils/client/rest/api/slurm_params.py
pyslurmutils/client/rest/api/slurm_response.py
pyslurmutils/client/rest/api/v0_0_39.py
pyslurmutils/client/rest/api/v0_0_40.py
pyslurmutils/client/rest/api/v0_0_41.py
pyslurmutils/client/rest/api/v0_0_42.py
pyslurmutils/concurrent/__init__.py
pyslurmutils/concurrent/futures.py
pyslurmutils/concurrent/rest.py
pyslurmutils/tests/__init__.py
pyslurmutils/tests/test_base.py
pyslurmutils/tests/test_remote_executor.py
pyslurmutils/tests/test_rest_executor.py
pyslurmutils-1.4.1.dist-info/licenses/LICENSE.md
pyslurmutils-1.4.1.dist-info/METADATA
pyslurmutils-1.4.1.dist-info/WHEEL
pyslurmutils-1.4.1.dist-info/entry_points.txt
pyslurmutils-1.4.1.dist-info/top_level.txt
pyslurmutils-1.4.1.dist-info/RECORD
