Metadata-Version: 2.4
Name: pyslurmutils
Version: 1.4.1
Summary: SLURM utilities for Python
Author-email: ESRF <dau-pydev@esrf.fr>
License: # MIT License
Project-URL: Homepage, https://gitlab.esrf.fr/workflow/pyslurmutils/
Project-URL: Documentation, https://pyslurmutils.readthedocs.io/
Project-URL: Repository, https://gitlab.esrf.fr/workflow/pyslurmutils/
Project-URL: Issues, https://gitlab.esrf.fr/workflow/pyslurmutils/issues
Project-URL: Changelog, https://gitlab.esrf.fr/workflow/pyslurmutils/-/blob/main/CHANGELOG.md
Classifier: Intended Audience :: Science/Research
Classifier: License :: OSI Approved :: MIT License
Classifier: Programming Language :: Python :: 3
Requires-Python: >=3.8
License-File: LICENSE.md
Requires-Dist: requests
Requires-Dist: tblib
Requires-Dist: tabulate
Requires-Dist: importlib_resources; python_version < "3.9"
Requires-Dist: pydantic>=2
Requires-Dist: pyjwt
Provides-Extra: test
Requires-Dist: pytest>=7; extra == "test"
Requires-Dist: pytest-timeout; extra == "test"
Provides-Extra: dev
Requires-Dist: pyslurmutils[test]; extra == "dev"
Requires-Dist: black>=25; extra == "dev"
Requires-Dist: flake8>=4; extra == "dev"
Requires-Dist: isort; extra == "dev"
Requires-Dist: datamodel-code-generator; extra == "dev"
Provides-Extra: doc
Requires-Dist: pyslurmutils[test]; extra == "doc"
Requires-Dist: sphinx>=4.5; extra == "doc"
Requires-Dist: sphinx-autodoc-typehints>=1.16; extra == "doc"
Requires-Dist: pydata-sphinx-theme<0.15; extra == "doc"
Requires-Dist: sphinx-copybutton; extra == "doc"
Requires-Dist: sphinx-argparse; extra == "doc"
Dynamic: license-file
